setup.py
Scripts/hello.py
tvt/__init__.py
tvt/tvt.py
tvt_test_vector_transformer.egg-info/PKG-INFO
tvt_test_vector_transformer.egg-info/SOURCES.txt
tvt_test_vector_transformer.egg-info/dependency_links.txt
tvt_test_vector_transformer.egg-info/top_level.txt