Metadata-Version: 1.1
Name: tvt-test-vector-transformer
Version: 0
Summary: Translate digital test vectors for automated test equipment for semiconductors
Home-page: https://github.com/gitfoxi/tvt-test-vector-transformer
Author: Michael Fox
Author-email: 415fox@gmail.com
License: UNKNOWN
Download-URL: https://github.com/gitfoxi/tvt-test-vector-transformer/tarball/master
Platform: UNKNOWN
Classifier: Development Status :: 3 - Alpha
Classifier: Topic :: Scientific/Engineering
Classifier: Topic :: Scientific/Engineering :: Electronic Design Automation (EDA)
Classifier: Operating System :: POSIX :: Linux
Classifier: Intended Audience :: Science/Research
Classifier: Programming Language :: Python
Classifier: Programming Language :: Python :: 2.7
